README.md
setup.py
joetags/__init__.py
joetags/__main__.py
joetags/add.py
joetags/browse.py
joetags/search.py
joetags.egg-info/PKG-INFO
joetags.egg-info/SOURCES.txt
joetags.egg-info/dependency_links.txt
joetags.egg-info/entry_points.txt
joetags.egg-info/top_level.txt