Metadata-Version: 2.1
Name: joetags
Version: 0.2.1
Summary: tag and organize your projects
Home-page: UNKNOWN
Author: realsirjoe
Maintainer: realsirjoe
License: UNKNOWN
Platform: UNKNOWN
